<?xml version="1.0" encoding="utf-8"?>
<savedqueries xmlns:xsi="http://www.w3.org/2001/XMLSchema-instance">
  <savedquery>
    <IsCustomizable>1</IsCustomizable>
    <CanBeDeleted>0</CanBeDeleted>
    <isquickfindquery>0</isquickfindquery>
    <isprivate>0</isprivate>
    <isdefault>1</isdefault>
    <savedqueryid>{6072346f-91ab-4b51-89ba-88c22c3a4425}</savedqueryid>
    <layoutxml>
      <grid name="resultset" jump="raw_name" select="1" icon="1" preview="1">
        <row name="result" id="raw_azuremapsconfigid">
          <cell name="raw_azuregovernment" width="150" imageproviderfunctionname="" imageproviderwebresource="$webresource:" />
          <cell name="raw_authenticationtype" width="200" imageproviderfunctionname="" imageproviderwebresource="$webresource:" />
          <cell name="createdon" width="125" />
          <cell name="createdby" width="100" />
        </row>
      </grid>
    </layoutxml>
    <querytype>1</querytype>
    <fetchxml>
      <fetch version="1.0" mapping="logical">
        <entity name="raw_azuremapsconfig">
          <attribute name="raw_azuremapsconfigid" />
          <attribute name="createdon" />
          <attribute name="raw_authenticationtype" />
          <attribute name="createdby" />
          <attribute name="raw_azuregovernment" />
          <order attribute="createdon" descending="false" />
        </entity>
      </fetch>
    </fetchxml>
    <IntroducedVersion>1.0.0.0</IntroducedVersion>
    <LocalizedNames>
      <LocalizedName description="Azure Maps Config Advanced Find View" languagecode="1033" />
    </LocalizedNames>
  </savedquery>
</savedqueries>